CONTRIBUTING.rst
HISTORY.rst
LICENSE
MANIFEST.in
README.rst
setup.cfg
setup.py
docs/modules.rst
docs/pang.helpers.rst
docs/pang.rst
pang/__init__.py
pang/cli.py
pang/generate_ansible.py
pang/pang.py
pang.egg-info/PKG-INFO
pang.egg-info/SOURCES.txt
pang.egg-info/dependency_links.txt
pang.egg-info/entry_points.txt
pang.egg-info/not-zip-safe
pang.egg-info/requires.txt
pang.egg-info/top_level.txt
pang/helpers/__init__.py
pang/helpers/files.py
pang/helpers/inventory.py
pang/helpers/nso.py
pang/helpers/playbook.py
pang/helpers/vars.py
tests/__init__.py
tests/test_pang.py