Metadata-Version: 1.1
Name: pang
Version: 0.1.0
Summary: A simple utility which will create Ansible playbooks for existing networks using NSO
Home-page: https://github.com/kecorbin/pang
Author: Kevin Corbin
Author-email: kecorbin@cisco.com
License: MIT license
Keywords: pang
Platform: UNKNOWN
Classifier: Development Status :: 2 - Pre-Alpha
Classifier: Intended Audience :: Developers
Classifier: License :: OSI Approved :: MIT License
Classifier: Natural Language :: English
Classifier: Programming Language :: Python :: 2
Classifier: Programming Language :: Python :: 2.7
Classifier: Programming Language :: Python :: 3
Classifier: Programming Language :: Python :: 3.4
Classifier: Programming Language :: Python :: 3.5
Classifier: Programming Language :: Python :: 3.6
Classifier: Programming Language :: Python :: 3.7
